ciostream-0.0.1.post8952160598.dist-info/LICENSE
ciostream-0.0.1.post8952160598.dist-info/METADATA
ciostream-0.0.1.post8952160598.dist-info/RECORD
ciostream-0.0.1.post8952160598.dist-info/top_level.txt
ciostream-0.0.1.post8952160598.dist-info/WHEEL
ciostream/core.cpython-37m-x86_64-linux-gnu.so
ciostream/core.pxd
ciostream/core.py
ciostream/__init__.py
ciostream/ciostream_native.cpp
ciostream/ciostream_native.h
