Metadata-Version: 2.1
Name: ciostream
Version: 0.0.1.post8952160598
Summary: Provides C++ iostream Cython wrappers
Home-page: UNKNOWN
Author: Matthew Ballance
Author-email: matt.ballance@gmail.com
License: UNKNOWN
Platform: UNKNOWN
License-File: LICENSE
